CHANGELOG
LICENSE
MANIFEST.in
README.md
setup.cfg
setup.py
test.py
Toucan.egg-info/PKG-INFO
Toucan.egg-info/SOURCES.txt
Toucan.egg-info/dependency_links.txt
Toucan.egg-info/entry_points.txt
Toucan.egg-info/not-zip-safe
Toucan.egg-info/requires.txt
Toucan.egg-info/top_level.txt
devtest6/__init__.py
devtest6/app_admin.py
devtest6/app_api.py
devtest6/app_app.py
devtest6/app_simple.py
devtest6/app_www.py
devtest6/manage.py
devtest6/application/__init__.py
devtest6/application/config.py
devtest6/application/exceptions.py
devtest6/application/model.py
devtest6/application/admin/__init__.py
devtest6/application/admin/views.py
devtest6/application/api/__init__.py
devtest6/application/api/views.py
devtest6/application/app/__init__.py
devtest6/application/app/views.py
devtest6/application/extras/__init__.py
devtest6/application/simple/__init__.py
devtest6/application/simple/views.py
devtest6/application/www/__init__.py
devtest6/application/www/views.py
tests/__init__.py
tests/config.py
tests/test_core.py
tests/test_decorators.py
tests/test_ext.py
tests/test_utils.py
webmaster/__about__.py
webmaster/__about__.pyc
webmaster/__init__.py
webmaster/__init__.pyc
webmaster/cli.py
webmaster/cli.pyc
webmaster/core.py
webmaster/core.pyc
webmaster/decorators.py
webmaster/decorators.pyc
webmaster/exceptions.py
webmaster/exceptions.pyc
webmaster/ext.py
webmaster/ext.pyc
webmaster/htmlcompress_ext.py
webmaster/htmlcompress_ext.pyc
webmaster/markdown_ext.py
webmaster/markdown_ext.pyc
webmaster/utils.py
webmaster/utils.pyc
webmaster/app-skel/__init__.py
webmaster/app-skel/app.py
webmaster/app-skel/blank
webmaster/app-skel/config.py
webmaster/app-skel/manage.py
webmaster/app-skel/model.py
webmaster/app-skel/propel.yml
webmaster/app-skel/data/mailer-templates/contact-us.txt
webmaster/app-skel/data/mailer-templates/default-template.txt
webmaster/app-skel/data/mailer-templates/reset-password.txt
webmaster/app-skel/data/mailer-templates/welcome-admin.txt
webmaster/app-skel/data/mailer-templates/welcome.txt
webmaster/app-skel/data/uploads/empty
webmaster/app-skel/skel/admin/__init__.py
webmaster/app-skel/skel/admin/views.py
webmaster/app-skel/skel/admin/static/assets.yml
